netstat2df/README.MD
netstat2df/__init__.py
netstat2df/requirements.txt
netstat2df/thirdparty.json
netstat2df-0.10.dist-info/LICENSE.rst
netstat2df-0.10.dist-info/METADATA
netstat2df-0.10.dist-info/WHEEL
netstat2df-0.10.dist-info/top_level.txt
netstat2df-0.10.dist-info/RECORD
