Metadata-Version: 2.1
Name: netstat2df
Version: 0.10
Summary: Retrieves and parses network statistics related to IPv4 TCP and UDP connection returns this information as a Pandas DataFrame
Home-page: https://github.com/hansalemaos/netstat2df
Author: Johannes Fischer
Author-email: aulasparticularesdealemaosp@gmail.com
License: MIT
Keywords: netstat,ipv4,tcp,udp
Classifier: Development Status :: 4 - Beta
Classifier: Programming Language :: Python :: 3 :: Only
Classifier: Programming Language :: Python :: 3.10
Classifier: Topic :: Software Development :: Libraries :: Python Modules
Classifier: Topic :: Utilities
License-File: LICENSE.rst
Requires-Dist: pandas
